django_user_sessions_ng/__init__.py
django_user_sessions_ng/admin.py
django_user_sessions_ng/apps.py
django_user_sessions_ng/geoip.py
django_user_sessions_ng/middleware.py
django_user_sessions_ng/models.py
django_user_sessions_ng/backends/__init__.py
django_user_sessions_ng/backends/cached_db.py
django_user_sessions_ng/backends/db.py
django_user_sessions_ng/management/__init__.py
django_user_sessions_ng/management/commands/__init__.py
django_user_sessions_ng/management/commands/clearsessions.py
django_user_sessions_ng/management/commands/download_geoip_db.py
django_user_sessions_ng/migrations/0001_initial.py
django_user_sessions_ng/migrations/__init__.py
django_user_sessions_ng-0.1.7.dist-info/METADATA
django_user_sessions_ng-0.1.7.dist-info/WHEEL
django_user_sessions_ng-0.1.7.dist-info/licenses/LICENSE
django_user_sessions_ng-0.1.7.dist-info/RECORD
