Metadata-Version: 2.3
Name: django-user-sessions-ng
Version: 0.1.7
Summary: Django User Sessions NG - a Django package to manage multiple user sessions.
Project-URL: Repository, https://github.com/yujinio/django-user-sessions-ng
Author-email: yujin <root@yujin.io>
License: MIT License
License-File: LICENSE
Keywords: django,django-user-sessions-ng,session-management,sessions
Requires-Python: >=3.12
Requires-Dist: django
Requires-Dist: django-admin-autocomplete-filter
Requires-Dist: django-ipware
Requires-Dist: user-agents
Provides-Extra: testing
Requires-Dist: pytest-django>=4.9.0; extra == 'testing'
Requires-Dist: pytest>=8.3.3; extra == 'testing'
